jaxfi/__init__.py
jaxfi/api.py
jaxfi/dynamic_lib_loading.py
jaxfi/enumerated_jnp_members.py
jaxfi/globals.py
jaxfi/types.py
jaxfi/utils.py
jaxfi/experimental/__init__.py
jaxfi/experimental/auto_pmap.py
jaxfi/experimental/device_cond.py
jaxfi/experimental/jit.py
jaxfi-0.7.3.dist-info/LICENSE
jaxfi-0.7.3.dist-info/METADATA
jaxfi-0.7.3.dist-info/WHEEL
jaxfi-0.7.3.dist-info/top_level.txt
jaxfi-0.7.3.dist-info/RECORD
