Metadata-Version: 2.1
Name: jaxfi
Version: 0.7.3
Summary: Friendly Interface to JAX, that behaves similar to PyTorch while maintaining compatibility.
Author: Robert Dyro
Author-email: Robert Dyro <robert.dyro@gmail.com>
Project-URL: Homepage, https://github.com/rdyro/jaxfi-JAXFriendlyInterface
Project-URL: Bug Tracker, https://github.com/rdyro/jaxfi-JAXFriendlyInterface
Classifier: Programming Language :: Python :: 3
Classifier: License :: OSI Approved :: MIT License
Classifier: Operating System :: OS Independent
Requires-Python: >=3.7
License-File: LICENSE
Requires-Dist: numpy
